{"flowContents":{"identifier":"7f893e83-04b7-36b3-ab5a-42576d53531b","instanceIdentifier":"26d38d1d-0198-1000-d889-20356e74b0b7","name":"Category","comments":"","position":{"x":-305.0,"y":-197.0},"processGroups":[],"remoteProcessGroups":[],"processors":[{"identifier":"0d96c292-0198-1000-27f4-2ab676c0c5e0","instanceIdentifier":"59029095-383b-3957-4e9d-06edc9d8c2b6","name":"ConsumeKafka","comments":"","position":{"x":-143.0,"y":-328.0},"type":"org.apache.nifi.kafka.processors.ConsumeKafka","bundle":{"group":"org.apache.nifi","artifact":"nifi-kafka-nar","version":"2.4.0"},"properties":{"Topics":"product","Commit Offsets":"true","Header Name Pattern":null,"Key Format":"byte-array","Key Record Reader":null,"Message Demarcator":null,"Record Reader":null,"Key Attribute Encoding":"utf-8","Topic Format":"names","Header Encoding":"UTF-8","Max Uncommitted Time":"100 millis","Kafka Connection Service":"7c8ff919-9e4a-34e3-a6f5-8e970637f057","Separate By Key":"false","Processing Strategy":"FLOW_FILE","Record Writer":null,"Group ID":"Category","auto.offset.reset":"latest","Output Strategy":"USE_VALUE"},"propertyDescriptors":{"Topics":{"name":"Topics","displayName":"Topics","identifiesControllerService":false,"sensitive":false,"dynamic":false},"Commit Offsets":{"name":"Commit Offsets","displayName":"Commit Offsets","identifiesControllerService":false,"sensitive":false,"dynamic":false},"Header Name Pattern":{"name":"Header Name Pattern","displayName":"Header Name Pattern","identifiesControllerService":false,"sensitive":false,"dynamic":false},"Key Format":{"name":"Key Format","displayName":"Key Format","identifiesControllerService":false,"sensitive":false,"dynamic":false},"Key Record Reader":{"name":"Key Record Reader","displayName":"Key Record Reader","identifiesControllerService":true,"sensitive":false,"dynamic":false},"Message Demarcator":{"name":"Message Demarcator","displayName":"Message Demarcator","identifiesControllerService":false,"sensitive":false,"dynamic":false},"Record Reader":{"name":"Record Reader","displayName":"Record Reader","identifiesControllerService":true,"sensitive":false,"dynamic":false},"Key Attribute Encoding":{"name":"Key Attribute Encoding","displayName":"Key Attribute Encoding","identifiesControllerService":false,"sensitive":false,"dynamic":false},"Topic Format":{"name":"Topic Format","displayName":"Topic Format","identifiesControllerService":false,"sensitive":false,"dynamic":false},"Header Encoding":{"name":"Header Encoding","displayName":"Header Encoding","identifiesControllerService":false,"sensitive":false,"dynamic":false},"Max Uncommitted Time":{"name":"Max Uncommitted Time","displayName":"Max Uncommitted Time","identifiesControllerService":false,"sensitive":false,"dynamic":false},"Kafka Connection Service":{"name":"Kafka Connection Service","displayName":"Kafka Connection Service","identifiesControllerService":true,"sensitive":false,"dynamic":false},"Separate By Key":{"name":"Separate By Key","displayName":"Separate By Key","identifiesControllerService":false,"sensitive":false,"dynamic":false},"Processing Strategy":{"name":"Processing Strategy","displayName":"Processing Strategy","identifiesControllerService":false,"sensitive":false,"dynamic":false},"Record Writer":{"name":"Record Writer","displayName":"Record Writer","identifiesControllerService":true,"sensitive":false,"dynamic":false},"Group ID":{"name":"Group ID","displayName":"Group ID","identifiesControllerService":false,"sensitive":false,"dynamic":false},"auto.offset.reset":{"name":"auto.offset.reset","displayName":"Auto Offset Reset","identifiesControllerService":false,"sensitive":false,"dynamic":false},"Output Strategy":{"name":"Output Strategy","displayName":"Output Strategy","identifiesControllerService":false,"sensitive":false,"dynamic":false}},"style":{},"schedulingPeriod":"0 sec","schedulingStrategy":"TIMER_DRIVEN","executionNode":"ALL","penaltyDuration":"30 sec","yieldDuration":"1 sec","bulletinLevel":"WARN","runDurationMillis":0,"concurrentlySchedulableTaskCount":1,"autoTerminatedRelationships":[],"scheduledState":"ENABLED","retryCount":10,"retriedRelationships":[],"backoffMechanism":"PENALIZE_FLOWFILE","maxBackoffPeriod":"10 mins","componentType":"PROCESSOR","groupIdentifier":"7f893e83-04b7-36b3-ab5a-42576d53531b"},{"identifier":"0d96c296-0198-1000-1e4f-14e56570ce16","instanceIdentifier":"8c0fdb46-d0f4-382a-9d66-a33ac14e25ad","name":"EvaluateJsonPath","comments":"","position":{"x":-135.0,"y":-120.0},"type":"org.apache.nifi.processors.standard.EvaluateJsonPath","bundle":{"group":"org.apache.nifi","artifact":"nifi-standard-nar","version":"2.4.0"},"properties":{"Destination":"flowfile-attribute","productId":"$.productId","Max String Length":"20 MB","Return Type":"auto-detect","Null Value Representation":"empty string","Path Not Found Behavior":"ignore"},"propertyDescriptors":{"Destination":{"name":"Destination","displayName":"Destination","identifiesControllerService":false,"sensitive":false,"dynamic":false},"productId":{"name":"productId","displayName":"productId","identifiesControllerService":false,"sensitive":false,"dynamic":true},"Max String Length":{"name":"Max String Length","displayName":"Max String Length","identifiesControllerService":false,"sensitive":false,"dynamic":false},"Return Type":{"name":"Return Type","displayName":"Return Type","identifiesControllerService":false,"sensitive":false,"dynamic":false},"Null Value Representation":{"name":"Null Value Representation","displayName":"Null Value Representation","identifiesControllerService":false,"sensitive":false,"dynamic":false},"Path Not Found Behavior":{"name":"Path Not Found Behavior","displayName":"Path Not Found Behavior","identifiesControllerService":false,"sensitive":false,"dynamic":false}},"style":{},"schedulingPeriod":"0 sec","schedulingStrategy":"TIMER_DRIVEN","executionNode":"ALL","penaltyDuration":"30 sec","yieldDuration":"1 sec","bulletinLevel":"WARN","runDurationMillis":0,"concurrentlySchedulableTaskCount":1,"autoTerminatedRelationships":[],"scheduledState":"ENABLED","retryCount":10,"retriedRelationships":[],"backoffMechanism":"PENALIZE_FLOWFILE","maxBackoffPeriod":"10 mins","componentType":"PROCESSOR","groupIdentifier":"7f893e83-04b7-36b3-ab5a-42576d53531b"},{"identifier":"0d96c295-0198-1000-b23f-9f844da6a182","instanceIdentifier":"6a95c21d-fab7-3ba7-cd5c-5dc95d514b2d","name":"PutS3Object","comments":"","position":{"x":-134.0,"y":112.0},"type":"org.apache.nifi.processors.aws.s3.PutS3Object","bundle":{"group":"org.apache.nifi","artifact":"nifi-aws-nar","version":"2.4.0"},"properties":{"FullControl User List":"${s3.permissions.full.users}","Owner":"${s3.owner}","proxy-configuration-service":null,"Resource Transfer Source":"FLOWFILE_CONTENT","Cache Control":null,"s3-object-remove-tags-prefix":"false","Endpoint Override URL":"http://minio:9000","File Resource Service":null,"Multipart Upload Max Age Threshold":"7 days","custom-signer-class-name":null,"canned-acl":"${s3.permissions.cannedacl}","custom-signer-module-location":null,"Signer Override":"Default Signature","Content Type":null,"server-side-encryption":"None","Write ACL User List":"${s3.permissions.writeacl.users}","encryption-service":null,"Read ACL User List":"${s3.permissions.readacl.users}","Content Disposition":null,"Storage Class":"Standard","Multipart Part Size":"5 GB","use-chunked-encoding":"true","Object Key":"product/${now():format(\"yyyy-MM-dd\")}/${productId}_${now():toNumber()}.json","AWS Credentials Provider service":"59a5f6ce-fbfa-300a-ad92-8f426cca2235","Multipart Threshold":"5 GB","s3-object-tags-prefix":null,"SSL Context Service":null,"Bucket":"bronze","Multipart Upload AgeOff Interval":"60 min","use-path-style-access":"false","Write Permission User List":"${s3.permissions.write.users}","Communications Timeout":"30 secs","Region":"us-west-2","Read Permission User List":"${s3.permissions.read.users}","Expiration Time Rule":null,"s3-temporary-directory-multipart":"${java.io.tmpdir}"},"propertyDescriptors":{"FullControl User List":{"name":"FullControl User List","displayName":"FullControl User List","identifiesControllerService":false,"sensitive":false,"dynamic":false},"Owner":{"name":"Owner","displayName":"Owner","identifiesControllerService":false,"sensitive":false,"dynamic":false},"proxy-configuration-service":{"name":"proxy-configuration-service","displayName":"Proxy Configuration Service","identifiesControllerService":true,"sensitive":false,"dynamic":false},"Resource Transfer Source":{"name":"Resource Transfer Source","displayName":"Resource Transfer Source","identifiesControllerService":false,"sensitive":false,"dynamic":false},"Cache Control":{"name":"Cache Control","displayName":"Cache Control","identifiesControllerService":false,"sensitive":false,"dynamic":false},"s3-object-remove-tags-prefix":{"name":"s3-object-remove-tags-prefix","displayName":"Remove Tag Prefix","identifiesControllerService":false,"sensitive":false,"dynamic":false},"Endpoint Override URL":{"name":"Endpoint Override URL","displayName":"Endpoint Override URL","identifiesControllerService":false,"sensitive":false,"dynamic":false},"File Resource Service":{"name":"File Resource Service","displayName":"File Resource Service","identifiesControllerService":true,"sensitive":false,"dynamic":false},"Multipart Upload Max Age Threshold":{"name":"Multipart Upload Max Age Threshold","displayName":"Multipart Upload Max Age Threshold","identifiesControllerService":false,"sensitive":false,"dynamic":false},"custom-signer-class-name":{"name":"custom-signer-class-name","displayName":"Custom Signer Class Name","identifiesControllerService":false,"sensitive":false,"dynamic":false},"canned-acl":{"name":"canned-acl","displayName":"Canned ACL","identifiesControllerService":false,"sensitive":false,"dynamic":false},"custom-signer-module-location":{"name":"custom-signer-module-location","displayName":"Custom Signer Module Location","identifiesControllerService":false,"sensitive":false,"dynamic":false,"resourceDefinition":{"cardinality":"MULTIPLE","resourceTypes":["DIRECTORY","FILE"]}},"Signer Override":{"name":"Signer Override","displayName":"Signer Override","identifiesControllerService":false,"sensitive":false,"dynamic":false},"Content Type":{"name":"Content Type","displayName":"Content Type","identifiesControllerService":false,"sensitive":false,"dynamic":false},"server-side-encryption":{"name":"server-side-encryption","displayName":"Server Side Encryption","identifiesControllerService":false,"sensitive":false,"dynamic":false},"Write ACL User List":{"name":"Write ACL User List","displayName":"Write ACL User List","identifiesControllerService":false,"sensitive":false,"dynamic":false},"encryption-service":{"name":"encryption-service","displayName":"Encryption Service","identifiesControllerService":true,"sensitive":false,"dynamic":false},"Read ACL User List":{"name":"Read ACL User List","displayName":"Read ACL User List","identifiesControllerService":false,"sensitive":false,"dynamic":false},"Content Disposition":{"name":"Content Disposition","displayName":"Content Disposition","identifiesControllerService":false,"sensitive":false,"dynamic":false},"Storage Class":{"name":"Storage Class","displayName":"Storage Class","identifiesControllerService":false,"sensitive":false,"dynamic":false},"Multipart Part Size":{"name":"Multipart Part Size","displayName":"Multipart Part Size","identifiesControllerService":false,"sensitive":false,"dynamic":false},"use-chunked-encoding":{"name":"use-chunked-encoding","displayName":"Use Chunked Encoding","identifiesControllerService":false,"sensitive":false,"dynamic":false},"Object Key":{"name":"Object Key","displayName":"Object Key","identifiesControllerService":false,"sensitive":false,"dynamic":false},"AWS Credentials Provider service":{"name":"AWS Credentials Provider service","displayName":"AWS Credentials Provider Service","identifiesControllerService":true,"sensitive":false,"dynamic":false},"Multipart Threshold":{"name":"Multipart Threshold","displayName":"Multipart Threshold","identifiesControllerService":false,"sensitive":false,"dynamic":false},"s3-object-tags-prefix":{"name":"s3-object-tags-prefix","displayName":"Object Tags Prefix","identifiesControllerService":false,"sensitive":false,"dynamic":false},"SSL Context Service":{"name":"SSL Context Service","displayName":"SSL Context Service","identifiesControllerService":true,"sensitive":false,"dynamic":false},"Bucket":{"name":"Bucket","displayName":"Bucket","identifiesControllerService":false,"sensitive":false,"dynamic":false},"Multipart Upload AgeOff Interval":{"name":"Multipart Upload AgeOff Interval","displayName":"Multipart Upload AgeOff Interval","identifiesControllerService":false,"sensitive":false,"dynamic":false},"use-path-style-access":{"name":"use-path-style-access","displayName":"Use Path Style Access","identifiesControllerService":false,"sensitive":false,"dynamic":false},"Write Permission User List":{"name":"Write Permission User List","displayName":"Write Permission User List","identifiesControllerService":false,"sensitive":false,"dynamic":false},"Communications Timeout":{"name":"Communications Timeout","displayName":"Communications Timeout","identifiesControllerService":false,"sensitive":false,"dynamic":false},"Region":{"name":"Region","displayName":"Region","identifiesControllerService":false,"sensitive":false,"dynamic":false},"Read Permission User List":{"name":"Read Permission User List","displayName":"Read Permission User List","identifiesControllerService":false,"sensitive":false,"dynamic":false},"Expiration Time Rule":{"name":"Expiration Time Rule","displayName":"Expiration Time Rule","identifiesControllerService":false,"sensitive":false,"dynamic":false},"s3-temporary-directory-multipart":{"name":"s3-temporary-directory-multipart","displayName":"Temporary Directory Multipart State","identifiesControllerService":false,"sensitive":false,"dynamic":false}},"style":{},"schedulingPeriod":"0 sec","schedulingStrategy":"TIMER_DRIVEN","executionNode":"ALL","penaltyDuration":"30 sec","yieldDuration":"1 sec","bulletinLevel":"WARN","runDurationMillis":0,"concurrentlySchedulableTaskCount":1,"autoTerminatedRelationships":[],"scheduledState":"ENABLED","retryCount":10,"retriedRelationships":[],"backoffMechanism":"PENALIZE_FLOWFILE","maxBackoffPeriod":"10 mins","componentType":"PROCESSOR","groupIdentifier":"7f893e83-04b7-36b3-ab5a-42576d53531b"}],"inputPorts":[],"outputPorts":[],"connections":[{"identifier":"0d96c2a2-0198-1000-0c58-4a941af0ae94","instanceIdentifier":"12cf4de9-fed6-3ea6-5455-11f84456513d","name":"","source":{"id":"0d96c295-0198-1000-b23f-9f844da6a182","type":"PROCESSOR","groupId":"7f893e83-04b7-36b3-ab5a-42576d53531b","name":"PutS3Object","comments":"","instanceIdentifier":"6a95c21d-fab7-3ba7-cd5c-5dc95d514b2d"},"destination":{"id":"0d96c29b-0198-1000-1b59-939f870689e7","type":"FUNNEL","groupId":"7f893e83-04b7-36b3-ab5a-42576d53531b","name":"Funnel","comments":"","instanceIdentifier":"7ba61fc7-c7c9-3227-645b-29263f30aab8"},"labelIndex":0,"zIndex":5,"selectedRelationships":["failure"],"backPressureObjectThreshold":10000,"backPressureDataSizeThreshold":"1 GB","flowFileExpiration":"0 sec","prioritizers":[],"bends":[],"loadBalanceStrategy":"DO_NOT_LOAD_BALANCE","partitioningAttribute":"","loadBalanceCompression":"DO_NOT_COMPRESS","componentType":"CONNECTION","groupIdentifier":"7f893e83-04b7-36b3-ab5a-42576d53531b"},{"identifier":"70d7a666-fdf3-3058-a26a-3c6c9e4a40b7","instanceIdentifier":"37443b36-4085-36af-5768-2799d93b2267","name":"","source":{"id":"0d96c292-0198-1000-27f4-2ab676c0c5e0","type":"PROCESSOR","groupId":"7f893e83-04b7-36b3-ab5a-42576d53531b","name":"ConsumeKafka","comments":"","instanceIdentifier":"59029095-383b-3957-4e9d-06edc9d8c2b6"},"destination":{"id":"0d96c296-0198-1000-1e4f-14e56570ce16","type":"PROCESSOR","groupId":"7f893e83-04b7-36b3-ab5a-42576d53531b","name":"EvaluateJsonPath","comments":"","instanceIdentifier":"8c0fdb46-d0f4-382a-9d66-a33ac14e25ad"},"labelIndex":0,"zIndex":6,"selectedRelationships":["success"],"backPressureObjectThreshold":10000,"backPressureDataSizeThreshold":"1 GB","flowFileExpiration":"0 sec","prioritizers":[],"bends":[],"loadBalanceStrategy":"DO_NOT_LOAD_BALANCE","partitioningAttribute":"","loadBalanceCompression":"DO_NOT_COMPRESS","componentType":"CONNECTION","groupIdentifier":"7f893e83-04b7-36b3-ab5a-42576d53531b"},{"identifier":"0d96c2a1-0198-1000-6b20-6b1b30e967bf","instanceIdentifier":"3518686f-9a0d-30b0-8e0a-ed5677ea47d7","name":"","source":{"id":"0d96c295-0198-1000-b23f-9f844da6a182","type":"PROCESSOR","groupId":"7f893e83-04b7-36b3-ab5a-42576d53531b","name":"PutS3Object","comments":"","instanceIdentifier":"6a95c21d-fab7-3ba7-cd5c-5dc95d514b2d"},"destination":{"id":"0d96c29a-0198-1000-2013-afba1ba825cc","type":"FUNNEL","groupId":"7f893e83-04b7-36b3-ab5a-42576d53531b","name":"Funnel","comments":"","instanceIdentifier":"d797e768-6172-3da9-8f79-bb85671fe015"},"labelIndex":0,"zIndex":4,"selectedRelationships":["success"],"backPressureObjectThreshold":10000,"backPressureDataSizeThreshold":"1 GB","flowFileExpiration":"0 sec","prioritizers":[],"bends":[],"loadBalanceStrategy":"DO_NOT_LOAD_BALANCE","partitioningAttribute":"","loadBalanceCompression":"DO_NOT_COMPRESS","componentType":"CONNECTION","groupIdentifier":"7f893e83-04b7-36b3-ab5a-42576d53531b"},{"identifier":"0d96c2a0-0198-1000-e2a9-6a0479d782c6","instanceIdentifier":"40b1f8e8-ced8-3ad1-e4bf-383d8d2e8e50","name":"","source":{"id":"0d96c296-0198-1000-1e4f-14e56570ce16","type":"PROCESSOR","groupId":"7f893e83-04b7-36b3-ab5a-42576d53531b","name":"EvaluateJsonPath","comments":"","instanceIdentifier":"8c0fdb46-d0f4-382a-9d66-a33ac14e25ad"},"destination":{"id":"0d96c299-0198-1000-67ba-4ff6deeaac0f","type":"FUNNEL","groupId":"7f893e83-04b7-36b3-ab5a-42576d53531b","name":"Funnel","comments":"","instanceIdentifier":"238d7008-c4c0-32aa-3dbd-9480862c00ef"},"labelIndex":0,"zIndex":3,"selectedRelationships":["failure","unmatched"],"backPressureObjectThreshold":10000,"backPressureDataSizeThreshold":"1 GB","flowFileExpiration":"0 sec","prioritizers":[],"bends":[],"loadBalanceStrategy":"DO_NOT_LOAD_BALANCE","partitioningAttribute":"","loadBalanceCompression":"DO_NOT_COMPRESS","componentType":"CONNECTION","groupIdentifier":"7f893e83-04b7-36b3-ab5a-42576d53531b"},{"identifier":"dc987637-232b-3004-94c9-b01075d84918","instanceIdentifier":"741dfb29-4ec4-36f3-9f92-04592a560184","name":"","source":{"id":"0d96c296-0198-1000-1e4f-14e56570ce16","type":"PROCESSOR","groupId":"7f893e83-04b7-36b3-ab5a-42576d53531b","name":"EvaluateJsonPath","comments":"","instanceIdentifier":"8c0fdb46-d0f4-382a-9d66-a33ac14e25ad"},"destination":{"id":"0d96c295-0198-1000-b23f-9f844da6a182","type":"PROCESSOR","groupId":"7f893e83-04b7-36b3-ab5a-42576d53531b","name":"PutS3Object","comments":"","instanceIdentifier":"6a95c21d-fab7-3ba7-cd5c-5dc95d514b2d"},"labelIndex":0,"zIndex":7,"selectedRelationships":["matched"],"backPressureObjectThreshold":10000,"backPressureDataSizeThreshold":"1 GB","flowFileExpiration":"0 sec","prioritizers":[],"bends":[],"loadBalanceStrategy":"DO_NOT_LOAD_BALANCE","partitioningAttribute":"","loadBalanceCompression":"DO_NOT_COMPRESS","componentType":"CONNECTION","groupIdentifier":"7f893e83-04b7-36b3-ab5a-42576d53531b"}],"labels":[{"identifier":"034bd446-339a-37fc-b28b-2a699aaa85ee","instanceIdentifier":"d8bf7d6c-ae0c-3688-d4e0-83f2e1de9460","position":{"x":-592.0,"y":-384.0},"label":"Category\n","zIndex":1,"width":1024.0,"height":752.0,"style":{"font-size":"18px"},"componentType":"LABEL","groupIdentifier":"7f893e83-04b7-36b3-ab5a-42576d53531b"}],"funnels":[{"identifier":"0d96c29b-0198-1000-1b59-939f870689e7","instanceIdentifier":"7ba61fc7-c7c9-3227-645b-29263f30aab8","position":{"x":-518.0,"y":256.0},"componentType":"FUNNEL","groupIdentifier":"7f893e83-04b7-36b3-ab5a-42576d53531b"},{"identifier":"0d96c299-0198-1000-67ba-4ff6deeaac0f","instanceIdentifier":"238d7008-c4c0-32aa-3dbd-9480862c00ef","position":{"x":-518.0,"y":-96.0},"componentType":"FUNNEL","groupIdentifier":"7f893e83-04b7-36b3-ab5a-42576d53531b"},{"identifier":"0d96c29a-0198-1000-2013-afba1ba825cc","instanceIdentifier":"d797e768-6172-3da9-8f79-bb85671fe015","position":{"x":-526.0,"y":80.0},"componentType":"FUNNEL","groupIdentifier":"7f893e83-04b7-36b3-ab5a-42576d53531b"}],"controllerServices":[{"identifier":"59a5f6ce-fbfa-300a-ad92-8f426cca2235","instanceIdentifier":"a77cb423-e5bd-3730-5f2c-208aa56df1fd","name":"AWSCredentialsProviderControllerService","comments":"","type":"org.apache.nifi.processors.aws.credentials.provider.service.AWSCredentialsProviderControllerService","bundle":{"group":"org.apache.nifi","artifact":"nifi-aws-nar","version":"2.4.0"},"properties":{"profile-name":null,"assume-role-proxy-configuration-service":null,"default-credentials":"false","Session Time":"3600","assume-role-ssl-context-service":null,"assume-role-sts-signer-override":"Default Signature","custom-signer-class-name":null,"Assume Role ARN":null,"custom-signer-module-location":null,"Assume Role Session Name":null,"assume-role-sts-endpoint":null,"assume-role-sts-region":"us-west-2","Credentials File":null,"assume-role-external-id":null,"anonymous-credentials":"false"},"propertyDescriptors":{"profile-name":{"name":"profile-name","displayName":"Profile Name","identifiesControllerService":false,"sensitive":false,"dynamic":false},"Access Key":{"name":"Access Key","displayName":"Access Key ID","identifiesControllerService":false,"sensitive":true,"dynamic":false},"assume-role-proxy-configuration-service":{"name":"assume-role-proxy-configuration-service","displayName":"Assume Role Proxy Configuration Service","identifiesControllerService":true,"sensitive":false,"dynamic":false},"default-credentials":{"name":"default-credentials","displayName":"Use Default Credentials","identifiesControllerService":false,"sensitive":false,"dynamic":false},"Session Time":{"name":"Session Time","displayName":"Assume Role Session Time","identifiesControllerService":false,"sensitive":false,"dynamic":false},"assume-role-ssl-context-service":{"name":"assume-role-ssl-context-service","displayName":"Assume Role SSL Context Service","identifiesControllerService":true,"sensitive":false,"dynamic":false},"assume-role-sts-signer-override":{"name":"assume-role-sts-signer-override","displayName":"Assume Role STS Signer Override","identifiesControllerService":false,"sensitive":false,"dynamic":false},"custom-signer-class-name":{"name":"custom-signer-class-name","displayName":"Custom Signer Class Name","identifiesControllerService":false,"sensitive":false,"dynamic":false},"Assume Role ARN":{"name":"Assume Role ARN","displayName":"Assume Role ARN","identifiesControllerService":false,"sensitive":false,"dynamic":false},"custom-signer-module-location":{"name":"custom-signer-module-location","displayName":"Custom Signer Module Location","identifiesControllerService":false,"sensitive":false,"dynamic":false,"resourceDefinition":{"cardinality":"MULTIPLE","resourceTypes":["DIRECTORY","FILE"]}},"Assume Role Session Name":{"name":"Assume Role Session Name","displayName":"Assume Role Session Name","identifiesControllerService":false,"sensitive":false,"dynamic":false},"assume-role-sts-endpoint":{"name":"assume-role-sts-endpoint","displayName":"Assume Role STS Endpoint Override","identifiesControllerService":false,"sensitive":false,"dynamic":false},"assume-role-sts-region":{"name":"assume-role-sts-region","displayName":"Assume Role STS Region","identifiesControllerService":false,"sensitive":false,"dynamic":false},"Secret Key":{"name":"Secret Key","displayName":"Secret Access Key","identifiesControllerService":false,"sensitive":true,"dynamic":false},"Credentials File":{"name":"Credentials File","displayName":"Credentials File","identifiesControllerService":false,"sensitive":false,"dynamic":false,"resourceDefinition":{"cardinality":"SINGLE","resourceTypes":["FILE"]}},"assume-role-external-id":{"name":"assume-role-external-id","displayName":"Assume Role External ID","identifiesControllerService":false,"sensitive":false,"dynamic":false},"anonymous-credentials":{"name":"anonymous-credentials","displayName":"Use Anonymous Credentials","identifiesControllerService":false,"sensitive":false,"dynamic":false}},"controllerServiceApis":[{"type":"org.apache.nifi.processors.aws.credentials.provider.AwsCredentialsProviderService","bundle":{"group":"org.apache.nifi","artifact":"nifi-aws-service-api-nar","version":"2.4.0"}},{"type":"org.apache.nifi.processors.aws.credentials.provider.service.AWSCredentialsProviderService","bundle":{"group":"org.apache.nifi","artifact":"nifi-aws-service-api-nar","version":"2.4.0"}}],"scheduledState":"DISABLED","bulletinLevel":"WARN","componentType":"CONTROLLER_SERVICE","groupIdentifier":"7f893e83-04b7-36b3-ab5a-42576d53531b"},{"identifier":"7c8ff919-9e4a-34e3-a6f5-8e970637f057","instanceIdentifier":"23db2aca-234d-326f-73fa-c21f1fe509ac","name":"Kafka3ConnectionService","comments":"","type":"org.apache.nifi.kafka.service.Kafka3ConnectionService","bundle":{"group":"org.apache.nifi","artifact":"nifi-kafka-3-service-nar","version":"2.4.0"},"properties":{"security.protocol":"PLAINTEXT","SSL Context Service":null,"ack.wait.time":"5 sec","sasl.username":null,"max.poll.records":"10000","sasl.mechanism":"GSSAPI","isolation.level":"read_committed","max.block.ms":"5 sec","bootstrap.servers":"http://kafka:9092","kerberos-user-service":null,"sasl.kerberos.service.name":null,"default.api.timeout.ms":"60 sec"},"propertyDescriptors":{"ack.wait.time":{"name":"ack.wait.time","displayName":"Acknowledgment Wait Time","identifiesControllerService":false,"sensitive":false,"dynamic":false},"sasl.username":{"name":"sasl.username","displayName":"SASL Username","identifiesControllerService":false,"sensitive":false,"dynamic":false},"max.poll.records":{"name":"max.poll.records","displayName":"Max Poll Records","identifiesControllerService":false,"sensitive":false,"dynamic":false},"bootstrap.servers":{"name":"bootstrap.servers","displayName":"Bootstrap Servers","identifiesControllerService":false,"sensitive":false,"dynamic":false},"sasl.kerberos.service.name":{"name":"sasl.kerberos.service.name","displayName":"Kerberos Service Name","identifiesControllerService":false,"sensitive":false,"dynamic":false},"security.protocol":{"name":"security.protocol","displayName":"Security Protocol","identifiesControllerService":false,"sensitive":false,"dynamic":false},"SSL Context Service":{"name":"SSL Context Service","displayName":"SSL Context Service","identifiesControllerService":true,"sensitive":false,"dynamic":false},"sasl.mechanism":{"name":"sasl.mechanism","displayName":"SASL Mechanism","identifiesControllerService":false,"sensitive":false,"dynamic":false},"isolation.level":{"name":"isolation.level","displayName":"Transaction Isolation Level","identifiesControllerService":false,"sensitive":false,"dynamic":false},"max.block.ms":{"name":"max.block.ms","displayName":"Max Metadata Wait Time","identifiesControllerService":false,"sensitive":false,"dynamic":false},"kerberos-user-service":{"name":"kerberos-user-service","displayName":"Kerberos User Service","identifiesControllerService":true,"sensitive":false,"dynamic":false},"sasl.password":{"name":"sasl.password","displayName":"SASL Password","identifiesControllerService":false,"sensitive":true,"dynamic":false},"default.api.timeout.ms":{"name":"default.api.timeout.ms","displayName":"Client Timeout","identifiesControllerService":false,"sensitive":false,"dynamic":false}},"controllerServiceApis":[{"type":"org.apache.nifi.kafka.service.api.KafkaConnectionService","bundle":{"group":"org.apache.nifi","artifact":"nifi-kafka-service-api-nar","version":"2.4.0"}}],"scheduledState":"DISABLED","bulletinLevel":"WARN","componentType":"CONTROLLER_SERVICE","groupIdentifier":"7f893e83-04b7-36b3-ab5a-42576d53531b"}],"defaultFlowFileExpiration":"0 sec","defaultBackPressureObjectThreshold":10000,"defaultBackPressureDataSizeThreshold":"1 GB","scheduledState":"ENABLED","executionEngine":"INHERITED","maxConcurrentTasks":1,"statelessFlowTimeout":"1 min","flowFileConcurrency":"UNBOUNDED","flowFileOutboundPolicy":"STREAM_WHEN_AVAILABLE","componentType":"PROCESS_GROUP"},"externalControllerServices":{},"parameterContexts":{},"flowEncodingVersion":"1.0","parameterProviders":{},"latest":false}